{
  "latest": {
    "date": "10/11/2021",
    "cdsPercent": 1,
    "cds": 27,
    "presentational": 0,
    "totalCdsAndPresentational": 27,
    "totalOther": 14
  },
  "previous": [
    {
      "date": "9/27/2021",
      "cdsPercent": 1,
      "cds": 27,
      "presentational": 0,
      "totalCdsAndPresentational": 27,
      "totalOther": 14
    },
    {
      "date": "10/5/2021",
      "cdsPercent": 1,
      "cds": 27,
      "presentational": 0,
      "totalCdsAndPresentational": 27,
      "totalOther": 14
    },
    {
      "date": "10/7/2021",
      "cdsPercent": 1,
      "cds": 27,
      "presentational": 0,
      "totalCdsAndPresentational": 27,
      "totalOther": 14
    }
  ]
}
