{
  "latest": {
    "date": "2/22/2022",
    "cdsPercent": 0.8986486486486487,
    "cds": 399,
    "presentational": 45,
    "totalCdsAndPresentational": 444,
    "totalOther": 268
  },
  "previous": [
    {
      "date": "9/27/2021",
      "cdsPercent": 0.8756476683937824,
      "cds": 338,
      "presentational": 48,
      "totalCdsAndPresentational": 386,
      "totalOther": 226
    },
    {
      "date": "10/5/2021",
      "cdsPercent": 0.875968992248062,
      "cds": 339,
      "presentational": 48,
      "totalCdsAndPresentational": 387,
      "totalOther": 226
    },
    {
      "date": "10/7/2021",
      "cdsPercent": 0.875968992248062,
      "cds": 339,
      "presentational": 48,
      "totalCdsAndPresentational": 387,
      "totalOther": 226
    },
    {
      "date": "10/11/2021",
      "cdsPercent": 0.875968992248062,
      "cds": 339,
      "presentational": 48,
      "totalCdsAndPresentational": 387,
      "totalOther": 226
    },
    {
      "date": "10/11/2021",
      "cdsPercent": 0.875968992248062,
      "cds": 339,
      "presentational": 48,
      "totalCdsAndPresentational": 387,
      "totalOther": 226
    },
    {
      "date": "10/20/2021",
      "cdsPercent": 0.8756218905472637,
      "cds": 352,
      "presentational": 50,
      "totalCdsAndPresentational": 402,
      "totalOther": 219
    },
    {
      "date": "10/27/2021",
      "cdsPercent": 0.8716707021791767,
      "cds": 360,
      "presentational": 53,
      "totalCdsAndPresentational": 413,
      "totalOther": 220
    },
    {
      "date": "11/8/2021",
      "cdsPercent": 0.8869179600886918,
      "cds": 400,
      "presentational": 51,
      "totalCdsAndPresentational": 451,
      "totalOther": 273
    },
    {
      "date": "11/19/2021",
      "cdsPercent": 0.890495867768595,
      "cds": 431,
      "presentational": 53,
      "totalCdsAndPresentational": 484,
      "totalOther": 286
    },
    {
      "date": "11/24/2021",
      "cdsPercent": 0.8857758620689655,
      "cds": 411,
      "presentational": 53,
      "totalCdsAndPresentational": 464,
      "totalOther": 278
    },
    {
      "date": "12/3/2021",
      "cdsPercent": 0.8997722095671982,
      "cds": 395,
      "presentational": 44,
      "totalCdsAndPresentational": 439,
      "totalOther": 299
    },
    {
      "date": "12/9/2021",
      "cdsPercent": 0.9006772009029346,
      "cds": 399,
      "presentational": 44,
      "totalCdsAndPresentational": 443,
      "totalOther": 267
    },
    {
      "date": "12/15/2021",
      "cdsPercent": 0.9009009009009009,
      "cds": 400,
      "presentational": 44,
      "totalCdsAndPresentational": 444,
      "totalOther": 268
    },
    {
      "date": "2/22/2022",
      "cdsPercent": 0.8986486486486487,
      "cds": 399,
      "presentational": 45,
      "totalCdsAndPresentational": 444,
      "totalOther": 268
    }
  ]
}
