{"latest":{"date":"4/27/2023","cdsPercent":0.7619974059662775,"cds":1175,"presentational":367,"totalCdsAndPresentational":1542,"totalOther":747},"previous":[{"date":"2/16/2022","cdsPercent":0.17724867724867724,"cds":134,"presentational":622,"totalCdsAndPresentational":756,"totalOther":674},{"date":"3/1/2022","cdsPercent":0.1871584699453552,"cds":137,"presentational":595,"totalCdsAndPresentational":732,"totalOther":641},{"date":"3/10/2022","cdsPercent":0.209366391184573,"cds":152,"presentational":574,"totalCdsAndPresentational":726,"totalOther":690},{"date":"3/16/2022","cdsPercent":0.2410596026490066,"cds":182,"presentational":573,"totalCdsAndPresentational":755,"totalOther":691},{"date":"3/23/2022","period":"Q1:2022","cdsPercent":0.2486910994764398,"cds":190,"presentational":574,"totalCdsAndPresentational":764,"totalOther":693},{"date":"4/21/2022","cdsPercent":0.25,"cds":192,"presentational":576,"totalCdsAndPresentational":768,"totalOther":702},{"date":"3/23/2022","period":"Q1:2022","cdsPercent":0.4926787252368648,"cds":572,"presentational":589,"totalCdsAndPresentational":1161,"totalOther":841},{"date":"7/14/2022","cdsPercent":0.49483648881239245,"cds":575,"presentational":587,"totalCdsAndPresentational":1162,"totalOther":840},{"date":"8/5/2022","cdsPercent":0.5046413502109705,"cds":598,"presentational":587,"totalCdsAndPresentational":1185,"totalOther":842},{"date":"8/17/2022","cdsPercent":0.48890784982935154,"cds":573,"presentational":599,"totalCdsAndPresentational":1172,"totalOther":850},{"date":"8/23/2022","cdsPercent":0.496215306980656,"cds":590,"presentational":599,"totalCdsAndPresentational":1189,"totalOther":853},{"date":"8/25/2022","cdsPercent":null,"cds":0,"presentational":0,"totalCdsAndPresentational":0,"totalOther":0},{"date":"8/29/2022","cdsPercent":0.5149006622516556,"cds":622,"presentational":586,"totalCdsAndPresentational":1208,"totalOther":855},{"date":"9/2/2022","cdsPercent":0.5232945091514143,"cds":629,"presentational":573,"totalCdsAndPresentational":1202,"totalOther":843},{"date":"9/6/2022","cdsPercent":0.5352226720647774,"cds":661,"presentational":574,"totalCdsAndPresentational":1235,"totalOther":849},{"date":"9/7/2022","cdsPercent":0.5526104417670683,"cds":688,"presentational":557,"totalCdsAndPresentational":1245,"totalOther":838},{"date":"9/9/2022","cdsPercent":0.5531746031746032,"cds":697,"presentational":563,"totalCdsAndPresentational":1260,"totalOther":836},{"date":"9/14/2022","cdsPercent":0.5545886075949367,"cds":701,"presentational":563,"totalCdsAndPresentational":1264,"totalOther":834},{"date":"9/21/2022","cdsPercent":0.5538945712037766,"cds":704,"presentational":567,"totalCdsAndPresentational":1271,"totalOther":837},{"date":"10/4/2022","cdsPercent":0.5143853530950305,"cds":590,"presentational":557,"period":"Q3:2022","totalCdsAndPresentational":1147,"totalOther":811},{"date":"10/14/2022","cdsPercent":0.5743913435527502,"cds":637,"presentational":472,"totalCdsAndPresentational":1109,"totalOther":715},{"date":"10/19/2022","cdsPercent":0.5783348254252462,"cds":646,"presentational":471,"totalCdsAndPresentational":1117,"totalOther":710},{"date":"10/26/2022","cdsPercent":0.5954063604240283,"cds":674,"presentational":458,"totalCdsAndPresentational":1132,"totalOther":693},{"date":"11/2/2022","cdsPercent":0.5961199294532628,"cds":676,"presentational":458,"totalCdsAndPresentational":1134,"totalOther":695},{"date":"11/9/2022","cdsPercent":0.627689429373246,"cds":671,"presentational":398,"totalCdsAndPresentational":1069,"totalOther":639},{"date":"11/17/2022","cdsPercent":0.642602495543672,"cds":721,"presentational":401,"totalCdsAndPresentational":1122,"totalOther":650},{"date":"11/30/2022","cdsPercent":0.648578811369509,"cds":753,"presentational":408,"totalCdsAndPresentational":1161,"totalOther":660},{"date":"12/6/2022","cdsPercent":0.6591478696741855,"cds":789,"presentational":408,"totalCdsAndPresentational":1197,"totalOther":665},{"date":"12/15/2022","cdsPercent":0.6655844155844156,"cds":820,"presentational":412,"totalCdsAndPresentational":1232,"totalOther":687},{"date":"1/17/2023","cdsPercent":0.669833729216152,"cds":846,"presentational":417,"period":"Q4:2022","totalCdsAndPresentational":1263,"totalOther":697},{"date":"1/17/2023","cdsPercent":0.669833729216152,"cds":846,"presentational":417,"totalCdsAndPresentational":1263,"totalOther":697},{"date":"1/25/2023","cdsPercent":0.6732128829536528,"cds":857,"presentational":416,"totalCdsAndPresentational":1273,"totalOther":708},{"date":"2/9/2023","cdsPercent":0.7109207708779444,"cds":996,"presentational":405,"totalCdsAndPresentational":1401,"totalOther":748},{"date":"2/16/2023","cdsPercent":0.7279461279461279,"cds":1081,"presentational":404,"totalCdsAndPresentational":1485,"totalOther":789},{"date":"2/23/2023","cdsPercent":0.7281292059219381,"cds":1082,"presentational":404,"totalCdsAndPresentational":1486,"totalOther":789},{"date":"2/28/2023","cdsPercent":0.7281292059219381,"cds":1082,"presentational":404,"totalCdsAndPresentational":1486,"totalOther":789},{"date":"3/9/2023","cdsPercent":0.7340355497037525,"cds":1115,"presentational":404,"totalCdsAndPresentational":1519,"totalOther":793},{"date":"3/15/2023","cdsPercent":0.7427217332430602,"cds":1097,"presentational":380,"totalCdsAndPresentational":1477,"totalOther":762},{"date":"3/22/2023","cdsPercent":0.742393509127789,"cds":1098,"presentational":381,"totalCdsAndPresentational":1479,"totalOther":762},{"date":"3/29/2023","cdsPercent":0.7518543492919757,"cds":1115,"presentational":368,"totalCdsAndPresentational":1483,"totalOther":746},{"date":"4/4/2023","cdsPercent":0.7520270270270271,"cds":1113,"presentational":367,"period":"Q1:2023","totalCdsAndPresentational":1480,"totalOther":747},{"date":"4/12/2023","cdsPercent":0.7506793478260869,"cds":1105,"presentational":367,"totalCdsAndPresentational":1472,"totalOther":746},{"date":"4/19/2023","cdsPercent":0.759344262295082,"cds":1158,"presentational":367,"totalCdsAndPresentational":1525,"totalOther":747}]}