{
  "latest": {
    "date": "2/16/2022",
    "cdsPercent": 0.15514809590973203,
    "cds": 110,
    "presentational": 599,
    "totalCdsAndPresentational": 709,
    "totalOther": 504
  },
  "previous": [
    {
      "date": "End of Q4",
      "cdsPercent": 0.15714285714285714,
      "cds": 44,
      "presentational": 236,
      "totalCdsAndPresentational": 280,
      "totalOther": 203
    },
    {
      "date": "1/26/2022",
      "cdsPercent": 0.15313935681470137,
      "cds": 100,
      "presentational": 553,
      "totalCdsAndPresentational": 653,
      "totalOther": 424
    },
    {
      "date": "2/4/2022",
      "cdsPercent": 0.15895953757225434,
      "cds": 110,
      "presentational": 582,
      "totalCdsAndPresentational": 692,
      "totalOther": 447
    },
    {
      "date": "2/9/2022",
      "cdsPercent": 0.15089163237311384,
      "cds": 110,
      "presentational": 619,
      "totalCdsAndPresentational": 729,
      "totalOther": 486
    },
    {
      "date": "2/16/2022",
      "cdsPercent": 0.1553672316384181,
      "cds": 110,
      "presentational": 598,
      "totalCdsAndPresentational": 708,
      "totalOther": 504
    }
  ]
}
